flowchem_test/__init__.py
flowchem_test/fakedevice.py
flowchem_test/py.typed
flowchem_test-0.1b5.dist-info/licenses/LICENSE
flowchem_test-0.1b5.dist-info/METADATA
flowchem_test-0.1b5.dist-info/WHEEL
flowchem_test-0.1b5.dist-info/entry_points.txt
flowchem_test-0.1b5.dist-info/top_level.txt
flowchem_test-0.1b5.dist-info/RECORD
